{
    "machine":  {
                    "system":  "PETRI_DISH_PRO_005C_AUTHORITATIVE_BOTTOM_OVERLAY",
                    "mode":  "resume_from_005B_visual_wound",
                    "repo":  "C:\\Users\\jacks\\OneDrive\\Desktop\\PetriDishPro",
                    "started_utc":  "2026-07-09T03:11:13.6520790Z",
                    "active_wound":  "bottom_boxes_visible_but_sized_wrong_and_not_loading_live_content",
                    "stage_policy":  "intended_files_only",
                    "claim_boundary":  "005C changes Electron UI layout/rendering only. It does not change simulation science, organisms, drug claims, antibody claims, wet-lab evidence, or clinical status.",
                    "status":  "sealed",
                    "finished_utc":  "2026-07-09T03:11:21.7116842Z",
                    "gates":  [
                                  {
                                      "gate":  "GATE_01_RESUME_FROM_005B",
                                      "status":  "pass",
                                      "utc":  "2026-07-09T03:11:13.8994260Z",
                                      "evidence":  {
                                                       "styles":  "visible",
                                                       "index":  "visible"
                                                   }
                                  },
                                  {
                                      "gate":  "GATE_02_BACKUP_INTENDED_FILES",
                                      "status":  "pass",
                                      "utc":  "2026-07-09T03:11:14.2376368Z",
                                      "evidence":  {
                                                       "backup_dir":  "C:\\Users\\jacks\\OneDrive\\Desktop\\PetriDishPro\\_backup\\petri_005c_20260708_231114",
                                                       "copied":  [
                                                                      "electron\\renderer\\index.html",
                                                                      "electron\\renderer\\styles.css",
                                                                      "README.md",
                                                                      "ROADMAP.md"
                                                                  ]
                                                   }
                                  },
                                  {
                                      "gate":  "GATE_03_WRITE_AUTHORITATIVE_OVERLAY_JS",
                                      "status":  "pass",
                                      "utc":  "2026-07-09T03:11:14.3098356Z",
                                      "evidence":  {
                                                       "js":  "electron/renderer/bottomAuthoritativeOverlay.js"
                                                   }
                                  },
                                  {
                                      "gate":  "GATE_04_PATCH_AUTHORITATIVE_OVERLAY_CSS",
                                      "status":  "pass",
                                      "utc":  "2026-07-09T03:11:14.8293047Z",
                                      "evidence":  {
                                                       "marker":  "PETRI 005C AUTHORITATIVE BOTTOM OVERLAY",
                                                       "css":  "electron/renderer/styles.css"
                                                   }
                                  },
                                  {
                                      "gate":  "GATE_05_BIND_SCRIPT_LAST",
                                      "status":  "pass",
                                      "utc":  "2026-07-09T03:11:15.9092911Z",
                                      "evidence":  {
                                                       "script":  "bottomAuthoritativeOverlay.js",
                                                       "order":  "last overlay owns bottom bar",
                                                       "index":  "electron/renderer/index.html"
                                                   }
                                  },
                                  {
                                      "gate":  "GATE_06_STATIC_AUTHORITATIVE_CONTRACT",
                                      "status":  "pass",
                                      "utc":  "2026-07-09T03:11:16.2955811Z",
                                      "evidence":  {
                                                       "contract":  "self-rendering bottom overlay present"
                                                   }
                                  },
                                  {
                                      "gate":  "GATE_07_RUN_NONSTRICT_TEST_DIGEST",
                                      "status":  "pass",
                                      "utc":  "2026-07-09T03:11:21.6351180Z",
                                      "evidence":  {
                                                       "note":  "non-strict; UI layout seal validated by static contract",
                                                       "digest_runner":  "ran",
                                                       "exit_code":  0
                                                   }
                                  },
                                  {
                                      "gate":  "GATE_08_PATCH_DOCS",
                                      "status":  "pass",
                                      "utc":  "2026-07-09T03:11:21.6654611Z",
                                      "evidence":  {
                                                       "doc":  "docs/updates/PETRI_005C_AUTHORITATIVE_BOTTOM_OVERLAY.md"
                                                   }
                                  },
                                  {
                                      "gate":  "GATE_09_OPTIONAL_INTENDED_FILES_GIT_SEAL",
                                      "status":  "pass",
                                      "utc":  "2026-07-09T03:11:21.7022770Z",
                                      "evidence":  {
                                                       "status":  "skipped",
                                                       "push":  false,
                                                       "commit":  false
                                                   }
                                  }
                              ]
                },
    "gates":  [
                  {
                      "gate":  "GATE_01_RESUME_FROM_005B",
                      "status":  "pass",
                      "utc":  "2026-07-09T03:11:13.8994260Z",
                      "evidence":  {
                                       "styles":  "visible",
                                       "index":  "visible"
                                   }
                  },
                  {
                      "gate":  "GATE_02_BACKUP_INTENDED_FILES",
                      "status":  "pass",
                      "utc":  "2026-07-09T03:11:14.2376368Z",
                      "evidence":  {
                                       "backup_dir":  "C:\\Users\\jacks\\OneDrive\\Desktop\\PetriDishPro\\_backup\\petri_005c_20260708_231114",
                                       "copied":  [
                                                      "electron\\renderer\\index.html",
                                                      "electron\\renderer\\styles.css",
                                                      "README.md",
                                                      "ROADMAP.md"
                                                  ]
                                   }
                  },
                  {
                      "gate":  "GATE_03_WRITE_AUTHORITATIVE_OVERLAY_JS",
                      "status":  "pass",
                      "utc":  "2026-07-09T03:11:14.3098356Z",
                      "evidence":  {
                                       "js":  "electron/renderer/bottomAuthoritativeOverlay.js"
                                   }
                  },
                  {
                      "gate":  "GATE_04_PATCH_AUTHORITATIVE_OVERLAY_CSS",
                      "status":  "pass",
                      "utc":  "2026-07-09T03:11:14.8293047Z",
                      "evidence":  {
                                       "marker":  "PETRI 005C AUTHORITATIVE BOTTOM OVERLAY",
                                       "css":  "electron/renderer/styles.css"
                                   }
                  },
                  {
                      "gate":  "GATE_05_BIND_SCRIPT_LAST",
                      "status":  "pass",
                      "utc":  "2026-07-09T03:11:15.9092911Z",
                      "evidence":  {
                                       "script":  "bottomAuthoritativeOverlay.js",
                                       "order":  "last overlay owns bottom bar",
                                       "index":  "electron/renderer/index.html"
                                   }
                  },
                  {
                      "gate":  "GATE_06_STATIC_AUTHORITATIVE_CONTRACT",
                      "status":  "pass",
                      "utc":  "2026-07-09T03:11:16.2955811Z",
                      "evidence":  {
                                       "contract":  "self-rendering bottom overlay present"
                                   }
                  },
                  {
                      "gate":  "GATE_07_RUN_NONSTRICT_TEST_DIGEST",
                      "status":  "pass",
                      "utc":  "2026-07-09T03:11:21.6351180Z",
                      "evidence":  {
                                       "note":  "non-strict; UI layout seal validated by static contract",
                                       "digest_runner":  "ran",
                                       "exit_code":  0
                                   }
                  },
                  {
                      "gate":  "GATE_08_PATCH_DOCS",
                      "status":  "pass",
                      "utc":  "2026-07-09T03:11:21.6654611Z",
                      "evidence":  {
                                       "doc":  "docs/updates/PETRI_005C_AUTHORITATIVE_BOTTOM_OVERLAY.md"
                                   }
                  },
                  {
                      "gate":  "GATE_09_OPTIONAL_INTENDED_FILES_GIT_SEAL",
                      "status":  "pass",
                      "utc":  "2026-07-09T03:11:21.7022770Z",
                      "evidence":  {
                                       "status":  "skipped",
                                       "push":  false,
                                       "commit":  false
                                   }
                  }
              ]
}
